[
  {
    "ParameterKey": "GitHubUser",
    "ParameterValue": "saty2485"
  },
  {
    "ParameterKey": "GitHubRepoName",
    "ParameterValue": "cicd-cfn"
  },
  {
    "ParameterKey": "SourceRepoBranch",
    "ParameterValue": "devo"
  },
  {
    "ParameterKey": "ReleaseBranch",
    "ParameterValue": "master"
  },
  {
    "ParameterKey": "GitHubOAuthToken",
    "ParameterValue": "c607fc43198d878571097b2d9c8eeba95e43671c"
  },
  {
    "ParameterKey": "QSS3BucketName",
    "ParameterValue": "$[taskcat_autobucket]"
  },
  {
    "ParameterKey": "QSS3BucketRegion",
    "ParameterValue": "$[taskcat_current_region]"
  },
  {
    "ParameterKey": "QSS3KeyPrefix",
    "ParameterValue": "quickstart-taskcat-ci/"
  }
]
